[
  {
    "name": "javafxTool",
    "description": "JavaFX scaffolding built on JDK21 + JavaFX 21 + controlsfx 11 + Maven.",
    "language": "Java",
    "stars": 17,
    "repo": "unknowIfGuestInDream/javafxTool"
  },
  {
    "name": "jvm-explorer",
    "description": "Desktop app for browsing loaded class files in running JVMs.",
    "language": "Java",
    "stars": 0,
    "repo": "unknowIfGuestInDream/jvm-explorer"
  },
  {
    "name": "InsightPC",
    "description": "Visual implementation of OSHI — view system and hardware information.",
    "language": "Java",
    "stars": 0,
    "repo": "unknowIfGuestInDream/InsightPC"
  },
  {
    "name": "patchVisualizer",
    "description": "Visualize patch files and their applied changes.",
    "language": "Java",
    "stars": 0,
    "repo": "unknowIfGuestInDream/patchVisualizer"
  },
  {
    "name": "dalian-dagunzi-fx",
    "description": "JavaFX 大连大骨子（个人趣味项目）。",
    "language": "Java",
    "stars": 0,
    "repo": "unknowIfGuestInDream/dalian-dagunzi-fx"
  },
  {
    "name": "eclipse-rcp-example",
    "description": "Eclipse RCP 示例工程。",
    "language": "Java",
    "stars": 1,
    "repo": "tlcsdm/eclipse-rcp-example"
  },
  {
    "name": "tlstudio",
    "description": "SWT examples (JFace / RCP examples planned).",
    "language": "Java",
    "stars": 2,
    "repo": "unknowIfGuestInDream/tlstudio"
  }
]
